MANIFEST.in
setup.py
M-ulator/simulator/.gitignore
M-ulator/simulator/Icon
M-ulator/simulator/README.build
M-ulator/simulator/Tupfile
M-ulator/simulator/Tupfile.ini
M-ulator/simulator/Tuprules.tup
M-ulator/simulator/run_tests.py
M-ulator/simulator/cli/Icon
M-ulator/simulator/cli/Tupfile
M-ulator/simulator/cli/cli.c
M-ulator/simulator/configs/373-debug
M-ulator/simulator/configs/373-debug-1
M-ulator/simulator/configs/373-debug-1-replay
M-ulator/simulator/configs/373-debug-2
M-ulator/simulator/configs/373-debug-2-nopipeline
M-ulator/simulator/configs/373-fast
M-ulator/simulator/configs/373-fast-nopipeline
M-ulator/simulator/configs/373-fast-nopipeline-debug
M-ulator/simulator/configs/373-release
M-ulator/simulator/configs/373-release-nopipeline
M-ulator/simulator/configs/373-release-replay
M-ulator/simulator/configs/Icon
M-ulator/simulator/configs/m3_ctl_v3-debug
M-ulator/simulator/configs/m3_ctl_v3-debug-1
M-ulator/simulator/configs/m3_ctl_v3-debug-2
M-ulator/simulator/configs/m3_ctl_v3-debug-2-nopipeline
M-ulator/simulator/configs/m3_ctl_v3-release
M-ulator/simulator/configs/m3_ctl_v3-release-nopipeline
M-ulator/simulator/configs/m3_prc_v9
M-ulator/simulator/configs/sam4l-debug
M-ulator/simulator/configs/sam4l-release
M-ulator/simulator/core/Icon
M-ulator/simulator/core/Tupfile
M-ulator/simulator/core/atomic_support.h
M-ulator/simulator/core/bintoarray.sh
M-ulator/simulator/core/common.h
M-ulator/simulator/core/conf.c
M-ulator/simulator/core/conf.h
M-ulator/simulator/core/ex_stage.c
M-ulator/simulator/core/ex_stage.h
M-ulator/simulator/core/gdb.c
M-ulator/simulator/core/gdb.h
M-ulator/simulator/core/id_stage.c
M-ulator/simulator/core/id_stage.h
M-ulator/simulator/core/if_stage.c
M-ulator/simulator/core/if_stage.h
M-ulator/simulator/core/loader.c
M-ulator/simulator/core/loader.h
M-ulator/simulator/core/opcodes.c
M-ulator/simulator/core/opcodes.h
M-ulator/simulator/core/pipeline.c
M-ulator/simulator/core/pipeline.h
M-ulator/simulator/core/pretty_print.h
PyMulator.egg-info/Icon
PyMulator.egg-info/PKG-INFO
PyMulator.egg-info/SOURCES.txt
PyMulator.egg-info/dependency_links.txt
PyMulator.egg-info/top_level.txt
