Metadata-Version: 1.0
Name: PyMulator
Version: 0.0.4
Summary: Library with a GDB-like interface for Mulator
Home-page: https://github.com/lukefahr/PyMulator
Author: Andrew Lukefahr
Author-email: UNKNOWN
License: UNKNOWN
Platform: UNKNOWN
